savebit/__init__.py
savebit/crypto.py
savebit/env.py
savebit/format/__init__.py
savebit/format/ini.py
savebit/format/json.py
savebit/format/pickle.py
savebit/format/yaml.py
SaveBit-1.0.dist-info/METADATA
SaveBit-1.0.dist-info/WHEEL
SaveBit-1.0.dist-info/top_level.txt
SaveBit-1.0.dist-info/RECORD
