Metadata-Version: 2.1
Name: SaveBit
Version: 1.0
Summary: 对多个数据持久化包进行封装
Author: moyan
Author-email: moyanjdc@qq.com
Classifier: Development Status :: 3 - Alpha
Classifier: Intended Audience :: Developers
Classifier: Programming Language :: Python :: 2.7
Classifier: Programming Language :: Python :: 3
Classifier: Programming Language :: Python :: 3.3
Classifier: Programming Language :: Python :: 3.4
Classifier: Programming Language :: Python :: 3.5
Classifier: Programming Language :: Python :: 3.6
Classifier: Programming Language :: Python :: 3.7
Classifier: Programming Language :: Python :: 3.8
Classifier: Programming Language :: Python :: 3.9
Classifier: Programming Language :: Python :: 3.10
Classifier: Programming Language :: Python :: 3.11
Requires-Dist: pyyaml
Requires-Dist: pycryptodome
Requires-Dist: msgpack
Provides-Extra: ai
Requires-Dist: h5py ; extra == 'ai'
Requires-Dist: csv ; extra == 'ai'
